<?xml version="1.0" encoding="UTF-8"?>
<odoo>
  <data noupdate="1">
    <record id="mail_template_rollup_subscription_renewed" model="mail.template">
      <field name="name">Rollup Subscription Renewed</field>
      <field name="model_id" ref="rollup_management.model_rollup_service"/>
      <field name="subject">Your Rollup subscription has been renewed 🎉</field>
      <field name="email_from">{{ (object.env.company.email_formatted or object.env.company.email) or 'support@zeeve.io' }}</field>
      <field name="email_to">{{ (ctx.get('rollup_subscription_ctx') or {}).get('email_to') or object.customer_id.email or (object.customer_id.user_ids[:1].partner_id.email) or '' }}</field>
      <field name="body_html"><![CDATA[
<t t-set="cfg" t-value="object.env['zeeve.config'].sudo().search([], limit=1)"/>
<t t-set="company" t-value="object.env.user.company_id or object.env['res.company'].sudo().search([], limit=1)"/>
<t t-set="base_url" t-value="(object.env['ir.config_parameter'].sudo().get_param('backend_url') or '').rstrip('/') or 'https://your-domain.example'"/>
<t t-set="company_logo" t-value="base_url + ('/web/image/res.company/%s/logo' % (company.id or 1))"/>
<t t-set="customer_name" t-value="(ctx.get('customer_name')) or (object.customer_id.display_name) or (object.customer_id.name) or (object.customer_id.user_ids[:1].partner_id.display_name) or (object.customer_id.user_ids[:1].partner_id.name) or 'there'"/>
<t t-set="invoice" t-value="ctx.get('invoice') or object._get_latest_invoice()"/>
<t t-set="payment" t-value="ctx.get('payment')"/>
<t t-set="currency" t-value="(payment and payment.currency_id) or (invoice and invoice.currency_id) or company.currency_id"/>
<t t-set="amount_value" t-value="payment and payment.amount or (invoice and invoice.amount_total) or 0.0"/>
<t t-set="formatted_amount" t-value="(formatLang and currency and formatLang(amount_value, currency_obj=currency)) or (currency and ('%s %s' % (currency.symbol or '', '%.2f' % amount_value))) or ('%.2f' % amount_value)"/>
<t t-set="invoice_url" t-value="ctx.get('stripe_invoice_url') or (invoice and invoice.get_portal_url())"/>
<t t-set="next_billing_raw" t-value="object.next_billing_date"/>
<t t-set="next_billing_display" t-value="(next_billing_raw and ((format_date and format_date(next_billing_raw)) or (hasattr(next_billing_raw, 'strftime') and next_billing_raw.strftime('%Y-%m-%d')) or str(next_billing_raw))) or 'TBA'"/>
<table align="center" border="0" cellpadding="0" cellspacing="0">
  <tr>
    <td style="padding:5px">
      <table align="center" border="0" cellpadding="0" cellspacing="0" style="border:1px solid #e9e9e9;background:#ffffff;" bgcolor="#ffffff">
        <tr>
          <td style="padding:24px 24px 10px 24px;">
            <table align="center" border="0" cellpadding="0" cellspacing="0">
              <tr>
                <td>
                  <a href="https://www.zeeve.io/">
                    <t t-if="company_logo">
                      <img t-att-src="company_logo" alt="Zeeve" height="80"/>
                    </t>
                    <t t-else="">
                      <img src="https://demo.studiobrahma.in/zeeve/mailer/images/zeeve-logo2.png" alt="Zeeve" height="80"/>
                    </t>
                  </a>
                </td>
              </tr>
              <tr>
                <td style="padding:18px 0 12px;">
                  <p style="font-size:20px;line-height:30px;font-weight:600;font-family:Poppins,Arial,Helvetica,sans-serif;margin:0;">
                    <strong>Hi <t t-out="customer_name"/>,</strong>
                  </p>
                </td>
              </tr>
              <tr>
                <td style="padding:0 0 18px;">
                  <p style="font-size:17px;line-height:26px;font-weight:400;font-family:Poppins,Arial,Helvetica,sans-serif;margin:0;">
                    Great news! Your payment for <strong><t t-out="object.name"/></strong> was successful and the subscription has been renewed without any downtime.
                  </p>
                </td>
              </tr>
              <tr>
                <td style="padding:20px 0 16px;">
                  <p style="font-size:15px;color:#FF9653;line-height:24px;font-weight:600;font-family:Poppins,Arial,Helvetica,sans-serif;margin:0;text-transform:uppercase;letter-spacing:4px;">Renewal Snapshot</p>
                </td>
              </tr>
              <tr>
                <td style="padding:0 0 10px;">
                  <table width="100%" border="0" cellpadding="0" cellspacing="0">
                    <tr>
                      <td style="padding:0 12px 12px 0;vertical-align:top;width:24px;">
                        <p style="font-size:18px;line-height:28px;font-weight:600;font-family:Poppins,Arial,Helvetica,sans-serif;color:#FF9653;margin:0;">&#9679;</p>
                      </td>
                      <td style="padding:0 0 12px 0;">
                        <p style="font-size:17px;line-height:24px;font-weight:500;font-family:Poppins,Arial,Helvetica,sans-serif;margin:0;">Invoice: <t t-out="invoice and invoice.display_name or 'N/A'"/></p>
                      </td>
                    </tr>
                    <tr>
                      <td style="padding:0 12px 12px 0;vertical-align:top;width:24px;">
                        <p style="font-size:18px;line-height:28px;font-weight:600;font-family:Poppins,Arial,Helvetica,sans-serif;color:#FF9653;margin:0;">&#9679;</p>
                      </td>
                      <td style="padding:0 0 12px 0;">
                        <p style="font-size:17px;line-height:24px;font-weight:500;font-family:Poppins,Arial,Helvetica,sans-serif;margin:0;">Amount paid: <t t-out="formatted_amount"/></p>
                      </td>
                    </tr>
                    <tr>
                      <td style="padding:0 12px 12px 0;vertical-align:top;width:24px;">
                        <p style="font-size:18px;line-height:28px;font-weight:600;font-family:Poppins,Arial,Helvetica,sans-serif;color:#FF9653;margin:0;">&#9679;</p>
                      </td>
                      <td style="padding:0 0 12px 0;">
                        <p style="font-size:17px;line-height:24px;font-weight:500;font-family:Poppins,Arial,Helvetica,sans-serif;margin:0;">Payment reference: <t t-out="payment and (payment.name or payment.ref) or 'N/A'"/></p>
                      </td>
                    </tr>
                    <tr>
                      <td style="padding:0 12px 12px 0;vertical-align:top;width:24px;">
                        <p style="font-size:18px;line-height:28px;font-weight:600;font-family:Poppins,Arial,Helvetica,sans-serif;color:#FF9653;margin:0;">&#9679;</p>
                      </td>
                      <td style="padding:0 0 12px 0;">
                        <p style="font-size:17px;line-height:24px;font-weight:500;font-family:Poppins,Arial,Helvetica,sans-serif;margin:0;">Next billing date: <t t-out="next_billing_display"/></p>
                      </td>
                    </tr>
                  </table>
                </td>
              </tr>
              <tr>
                <td style="padding:12px 0 24px;">
                  <t t-if="invoice_url">
                    <a t-att-href="invoice_url" style="display:inline-block;padding:12px 28px;background:#FF9653;color:#ffffff;font-size:15px;font-weight:600;font-family:Poppins,Arial,Helvetica,sans-serif;border-radius:6px;text-decoration:none;">View Invoice</a>
                  </t>
                </td>
              </tr>
              <tr>
                <td style="padding:0 0 18px;">
                  <p style="font-size:16px;line-height:26px;font-weight:400;font-family:Poppins,Arial,Helvetica,sans-serif;margin:0;">
                    We're already provisioning the next cycle—no further action is required from your side.
                  </p>
                </td>
              </tr>
              <tr>
                <td style="padding:0 0 18px;">
                  <p style="font-size:16px;line-height:26px;font-weight:400;font-family:Poppins,Arial,Helvetica,sans-serif;margin:0;">
                    Questions? Reach us at <a t-att-href="'mailto:%s' % ((cfg and cfg.support_email) or 'support@zeeve.io')" style="color:#FF9653;text-decoration:none;"><t t-out="(cfg and cfg.support_email) or 'support@zeeve.io'"/></a>.
                  </p>
                </td>
              </tr>
              <tr>
                <td style="padding:0 0 24px;">
                  <p style="font-size:17px;line-height:26px;font-weight:500;font-family:Poppins,Arial,Helvetica,sans-serif;margin:0;">With appreciation,<br/>The Zeeve Team</p>
                </td>
              </tr>
            </table>
          </td>
        </tr>
      </table>
    </td>
  </tr>
</table>
      ]]></field>
    </record>
  </data>
</odoo>
